erniekit/__init__.py
erniekit/cli.py
erniekit/launcher.py
erniekit/chat/__init__.py
erniekit/chat/chat.py
erniekit/chat/server.py
erniekit/eval/__init__.py
erniekit/eval/eval.py
erniekit/export/__init__.py
erniekit/export/export.py
erniekit/export/split.py
erniekit/hparams/__init__.py
erniekit/hparams/data_args.py
erniekit/hparams/export_args.py
erniekit/hparams/finetuning_args.py
erniekit/hparams/generating_args.py
erniekit/hparams/model_args.py
erniekit/hparams/parser.py
erniekit/hparams/preprocess_args.py
erniekit/hparams/server_args.py
erniekit/train/__init__.py
erniekit/train/tuner.py
erniekit/train/dpo/__init__.py
erniekit/train/dpo/dpo_estimate_training.py
erniekit/train/dpo/dpo_utils.py
erniekit/train/dpo/trainer.py
erniekit/train/dpo/workflow.py
erniekit/train/sft/__init__.py
erniekit/train/sft/trainer.py
erniekit/train/sft/workflow.py
erniekit/train/vl_sft/__init__.py
erniekit/train/vl_sft/pretraining_trainer.py
erniekit/train/vl_sft/trainer.py
erniekit/train/vl_sft/workflow.py
erniekit/utils/__init__.py
erniekit/utils/process.py
erniekit/version/__init__.py
erniekit/version/env.py
erniekit/version/git.py
erniekit/webui/__init__.py
erniekit/webui/alert.py
erniekit/webui/chatbot.py
erniekit/webui/common.py
erniekit/webui/control.py
erniekit/webui/lang.py
erniekit/webui/manager.py
erniekit/webui/runner.py
erniekit/webui/webui.py
erniekit/webui/view/__init__.py
erniekit/webui/view/basic.py
erniekit/webui/view/chat.py
erniekit/webui/view/eval.py
erniekit/webui/view/export.py
erniekit/webui/view/style.py
erniekit/webui/view/train.py
erniekit-1.3.0.dist-info/licenses/LICENSE
erniekit-1.3.0.dist-info/METADATA
erniekit-1.3.0.dist-info/WHEEL
erniekit-1.3.0.dist-info/entry_points.txt
erniekit-1.3.0.dist-info/top_level.txt
erniekit-1.3.0.dist-info/RECORD
