Metadata-Version: 2.4
Name: erniekit
Version: 1.3.0
Summary: The official repository for ERNIE 4.5 and ERNIEKit - its industrial-grade development toolkit based on PaddlePaddle.
Home-page: https://github.com/PaddlePaddle/ERNIE
Maintainer: PaddlePaddle
Maintainer-email: Paddle-better@baidu.com
License: Apache 2.0 License
License-File: LICENSE
Requires-Dist: paddleformers==0.3.1
Requires-Dist: setuptools==79.0.1
Requires-Dist: decord
Requires-Dist: moviepy
Requires-Dist: GPUtil
Requires-Dist: openai
Requires-Dist: gradio
Requires-Dist: opencv-python==4.5.5.64
Requires-Dist: imgaug==0.4.0
Requires-Dist: triton==3.3
Requires-Dist: use-triton-in-paddle
Requires-Dist: tensorboardX
Requires-Dist: ujson
Dynamic: description
Dynamic: description-content-type
Dynamic: home-page
Dynamic: license
Dynamic: license-file
Dynamic: maintainer
Dynamic: maintainer-email
Dynamic: requires-dist
Dynamic: summary
